<Properties StartupConfiguration="{96ED7638-F2F9-447D-90D2-5E8F887BF14D}|Default">
  <MonoDevelop.Ide.ItemProperties.Apps.MyFirstMvcApp PreferredExecutionTarget="MonoDevelop.Default" />
  <MonoDevelop.Ide.Workbench ActiveDocument="MyFirstMvcApp/Controllers/HomeController.cs">
    <Files>
      <File FileName="MyFirstMvcApp/Controllers/HomeController.cs" Line="13" Column="1" />
      <File FileName="MyFirstMvcApp/Startup.cs" Line="19" Column="10" />
      <File FileName="SUS.MvcFramework/Host.cs" Line="67" Column="74" />
      <File FileName="SUS.MvcFramework/Controller.cs" Line="17" Column="15" />
    </Files>
    <Pads>
      <Pad Id="ProjectPad">
        <State name="__root__">
          <Node name="SUS" expanded="True">
            <Node name="Apps" expanded="True">
              <Node name="MyFirstMvcApp" expanded="True">
                <Node name="Controllers" expanded="True">
                  <Node name="HomeController.cs" selected="True" />
                </Node>
                <Node name="ViewModels" expanded="True" />
                <Node name="Views" expanded="True">
                  <Node name="Home" expanded="True" />
                </Node>
              </Node>
            </Node>
            <Node name="SUS.MvcFramework" expanded="True" />
          </Node>
        </State>
      </Pad>
    </Pads>
  </MonoDevelop.Ide.Workbench>
  <MonoDevelop.Ide.DebuggingService.PinnedWatches />
  <MonoDevelop.Ide.Workspace ActiveConfiguration="Debug" />
  <MonoDevelop.Ide.DebuggingService.Breakpoints>
    <BreakpointStore />
  </MonoDevelop.Ide.DebuggingService.Breakpoints>
  <MultiItemStartupConfigurations />
</Properties>